eks_crutch/__init__.py
eks_crutch/cli.py
eks_crutch/eks_crutch.py
eks_crutch-0.1.1.dist-info/AUTHORS.rst
eks_crutch-0.1.1.dist-info/LICENSE
eks_crutch-0.1.1.dist-info/METADATA
eks_crutch-0.1.1.dist-info/WHEEL
eks_crutch-0.1.1.dist-info/entry_points.txt
eks_crutch-0.1.1.dist-info/top_level.txt
eks_crutch-0.1.1.dist-info/RECORD
