Metadata-Version: 2.1
Name: eks-crutch
Version: 0.1.1
Summary: Wrapper script to run programs using the IAM role associated with a ServiceAccount
Home-page: https://github.com/seanlynch/eks_crutch
Author: Sean R. Lynch
Author-email: sean@foghornconsulting.com
License: Apache Software License 2.0
Keywords: eks_crutch
Platform: UNKNOWN
Classifier: Development Status :: 2 - Pre-Alpha
Classifier: Intended Audience :: Developers
Classifier: License :: OSI Approved :: Apache Software License
Classifier: Natural Language :: English
Classifier: Programming Language :: Python :: 3
Classifier: Programming Language :: Python :: 3.5
Classifier: Programming Language :: Python :: 3.6
Classifier: Programming Language :: Python :: 3.7
Classifier: Programming Language :: Python :: 3.8
Requires-Python: >=3.5
Requires-Dist: boto3
